tphat/__init__.py
tphat/_aevents.py
tphat/_client.py
tphat/_core.py
tphat/_exception.py
tphat/_message.py
tphat/_objects.py
tphat/_package.py
tphat/_parse_message.py
tphat/_state.py
tphat/_threads.py
tphat/_util.py
tphat/_version.py
tphat/logging.py
tphat/models.py
tphat-0.0.1.dist-info/METADATA
tphat-0.0.1.dist-info/WHEEL
tphat-0.0.1.dist-info/top_level.txt
tphat-0.0.1.dist-info/RECORD
