Metadata-Version: 2.4
Name: tphat
Version: 0.0.1
Summary: package
Author-email: khah <trchikhanhfrv@gmail.com>
License: MIT
Requires-Python: >=3.8
